AUTHORS
MANIFEST.in
README
setup.py
src/django_future/__init__.py
src/django_future/admin.py
src/django_future/models.py
src/django_future/tests.py
src/django_future/tests.txt
src/django_future/utils.py
src/django_future.egg-info/PKG-INFO
src/django_future.egg-info/SOURCES.txt
src/django_future.egg-info/dependency_links.txt
src/django_future.egg-info/requires.txt
src/django_future.egg-info/top_level.txt
src/django_future/locale/de/LC_MESSAGES/django.mo
src/django_future/locale/de/LC_MESSAGES/django.po
src/django_future/locale/en/LC_MESSAGES/django.po
src/django_future/management/__init__.py
src/django_future/management/commands/__init__.py
src/django_future/management/commands/runscheduledjobs.py