Metadata-Version: 1.0
Name: django-future
Version: 0.2.2
Summary: Scheduled jobs in Django
Home-page: http://github.com/shrubberysoft/django-future
Author: Shrubbery Software
Author-email: team@shrubberysoft.com
License: UNKNOWN
Platform: UNKNOWN
Classifier: Development Status :: 4 - Beta
Classifier: Framework :: Django
Classifier: License :: OSI Approved :: MIT License
